nice_crud/__init__.py
nice_crud/constants.py
nice_crud/exceptions.py
nice_crud/helper.py
nice_crud/psql.py
nice_crud-0.0.2.dist-info/METADATA
nice_crud-0.0.2.dist-info/WHEEL
nice_crud-0.0.2.dist-info/top_level.txt
nice_crud-0.0.2.dist-info/RECORD
