Metadata-Version: 2.1
Name: nice-crud
Version: 0.0.2
Summary: A simple CRUD application
Home-page: https://github.com/amiwrpremium/nice_crud
Author: amiwrpremium
Author-email: amiwrpremiun@gmail.com
License: MIT
Project-URL: Bug Tracker, https://github.com/amiwrpremium/nice_crud/issues
Keywords: crud,crud-app,crud-application
Platform: UNKNOWN
Classifier: Development Status :: 3 - Alpha
Classifier: Intended Audience :: Developers
Classifier: License :: OSI Approved :: MIT License
Classifier: Programming Language :: Python :: 3.6
Classifier: Topic :: Software Development :: Libraries :: Python Modules
Requires-Python: >=3.8.10
Requires-Dist: psycopg2-binary
